MANIFEST.in
README.md
setup.py
pipelinetweak/__init__.py
pipelinetweak.egg-info/PKG-INFO
pipelinetweak.egg-info/SOURCES.txt
pipelinetweak.egg-info/dependency_links.txt
pipelinetweak.egg-info/not-zip-safe
pipelinetweak.egg-info/requires.txt
pipelinetweak.egg-info/top_level.txt
test/__init__.py
test/test_predt.py